testnet/__init__.py
testnet/interfaces/__init__.py
testnet/interfaces/address_balance_interface.py
testnet/interfaces/address_create_interface.py
testnet/interfaces/logs/__init__.py
testnet/interfaces/logs/logs_interface.py
testnet/interfaces/logs/meta.py
testnet/wallets/__init__.py
testnet/wallets/btc/__init__.py
testnet/wallets/btc/balance.py
testnet/wallets/btc/create.py
testnet/wallets/btc/transaction.py
testnet/wallets/eth/__init__.py
testnet/wallets/eth/balance.py
testnet/wallets/eth/create.py
testnet/wallets/eth/transaction.py
testnet/wallets/sol/__init__.py
testnet/wallets/sol/balance.py
testnet/wallets/sol/create.py
testnet/wallets/sol/transaction.py
testnet/wallets/trx/__init__.py
testnet/wallets/trx/balance.py
testnet/wallets/trx/create.py
testnet/wallets/trx/transaction.py
nextvibetestnet-0.3.1.dist-info/METADATA
nextvibetestnet-0.3.1.dist-info/WHEEL
nextvibetestnet-0.3.1.dist-info/top_level.txt
nextvibetestnet-0.3.1.dist-info/RECORD
