Metadata-Version: 2.4
Name: NextVibeTestnet
Version: 0.3.1
Summary: A library for work with testnet wallets bitcoin, solana and tron
Home-page: https://github.com/hardusss/TestnetWallets.git
Author: Hard
Author-email: danylo29bro@gmail.com
Classifier: Programming Language :: Python :: 3
Classifier: License :: OSI Approved :: MIT License
Requires-Dist: solana==0.27.0
Requires-Dist: tronpy==0.5.0
Requires-Dist: bitcoinlib==0.7.1
Requires-Dist: requests==2.32.3
Requires-Dist: python-dotenv==1.0.1
Dynamic: author
Dynamic: author-email
Dynamic: classifier
Dynamic: description-content-type
Dynamic: home-page
Dynamic: requires-dist
Dynamic: summary
